.DS_Store
ans/__init__.py
ans_python-0.3.1.dist-info/METADATA
ans_python-0.3.1.dist-info/WHEEL
ans_python-0.3.1.dist-info/top_level.txt
ans_python-0.3.1.dist-info/RECORD
